{"start time": "2019-12-04 20:27:27.467297", "row_count": 138, "dataset_name": "53jv-eiur.tsv.gz", "columns": [{"column_name": "DBN", "number_non_empty_cells": 138, "number_empty_cells": 0, "number_distinct_values": 138, "frequent_values": ["01M015", "01M020", "01M063", "01M064", "02M011"], "dataTypes": [{"type": "Text", "count": 134, "longest_values": ["01M063", "01M064", "02M077", "02M124", "02M130"], "shortest_values": ["01M063", "01M064", "02M077", "02M124", "02M130"], "average_length": 6.0}, {"type": "Date/Time", "count": 4, "max_value": "2019-12-04 00:06:28", "min_value": "2019-12-04 00:01:15"}]}, {"column_name": "School Name", "number_non_empty_cells": 138, "number_empty_cells": 0, "number_distinct_values": 138, "frequent_values": ["P.S. 15 Roberto Clemente (01M015)", "P.S. 020 Anna Silver (01M020)", "P.S. 63 William McKinley (01M063)", "P.S. 64 Robert Simon (01M064)", "P.S. 11 William T. Harris (02M011)"], "dataTypes": [{"type": "Text", "count": 138, "longest_values": ["P.S./I.S. 210 - Twenty-first Century Academy for Community Leadership (06M210)", "P.S./I.S. 218 Rafael Hernandez Dual Language Magnet School (09X218)", "The Queens College School for Math, Science and Technology (25Q499)", "P.S. 264 Bay Ridge Elementary School for the Arts (20K264)", "P.S. 262 El Hajj Malik Shabazz Elementary School (16K262)"], "shortest_values": ["P.S. 78 (30Q078)", "P.S. 95 (29Q095)", "P.S. 96 (27Q096)", "P.S. 006 (17K006)", "P.S. 119 (08X119)"], "average_length": 33.507246376811594}]}], "col_count": 3, "key_column_candidates": ["DBN", "School Name"], "end time": "2019-12-04 20:27:27.724036"}