{"start time": "2019-12-04 23:24:28.868737", "row_count": 8771, "dataset_name": "96ay-ea4r.tsv.gz", "columns": [{"column_name": "ID", "number_non_empty_cells": 8771, "number_empty_cells": 0, "number_distinct_values": 120, "frequent_values": ["3", "12", "2", "7", "14"], "dataTypes": [{"type": "Integer", "count": 8771, "max_val": 120, "min_val": 1, "mean": 54.37270550678372, "std_dev": 34.66398507874055}]}, {"column_name": "SegmentID", "number_non_empty_cells": 8771, "number_empty_cells": 0, "number_distinct_values": 527, "frequent_values": ["19566", "2933", "10335", "22921", "26932"], "dataTypes": [{"type": "Integer", "count": 8771, "max_val": 9014216, "min_val": 2367, "mean": 443976.30566640064, "std_dev": 1747292.5847936943}]}, {"column_name": "Roadway Name", "number_non_empty_cells": 8771, "number_empty_cells": 0, "number_distinct_values": 315, "frequent_values": ["FDR Drive", "Metropolitan Avenue", "Jamaica Avenue", "Ocean Parkway", "EAST 167 STREET"], "dataTypes": [{"type": "Text", "count": 8771, "longest_values": ["Bruckner Expressway/Boulevard Service Road", "EB ED Koch Queensboro Bridge Upper Level", "WB ED Koch Queensboro Bridge Lower Level", "WB ED Koch Queensboro Bridge Upper Level", "Bruckner Expressway/Boulevard Main Road"], "shortest_values": ["BQE", "56 Road", "1 AVENUE", "1 Avenue", "115 Road"], "average_length": 14.598221411469616}]}, {"column_name": "From", "number_non_empty_cells": 8771, "number_empty_cells": 0, "number_distinct_values": 393, "frequent_values": ["47 Street", "CLOVE ROAD", "72 STREET", "73 Street", "176 STREET"], "dataTypes": [{"type": "Text", "count": 8771, "longest_values": ["Roosevelt Island Shoreline", "Manhattan Bridge Approach", "CROSS BRONX EXPWY NB SR", "FRANCIS LEWIS BOULEVARD", "Long Island Expressway"], "shortest_values": ["FDR", "BRIDGE", "46 Road", "64 Road", "68 ROAD"], "average_length": 12.223463687150838}]}, {"column_name": "To", "number_non_empty_cells": 8771, "number_empty_cells": 0, "number_distinct_values": 393, "frequent_values": ["72 Street", "73 STREET", "48 Street", "West 12 Street", "39 Avenue"], "dataTypes": [{"type": "Text", "count": 8771, "longest_values": ["NEW ENGLAND THRUWAY ENTRANCE", "Roosevelt Island Shoreline", "VAN COURTLANDT PARK SOUTH", "E MOSHOLU PARKWAY SOUTH", "FRANCIS LEWIS BOULEVARD"], "shortest_values": ["FDR", "Bowery", "47 ROAD", "68 ROAD", "85 ROAD"], "average_length": 12.609736632083}]}, {"column_name": "Direction", "number_non_empty_cells": 8771, "number_empty_cells": 0, "number_distinct_values": 5, "frequent_values": ["NB", "SB", "EB", "WB", "EB&WB"], "dataTypes": [{"type": "Text", "count": 8771, "longest_values": ["EB&WB", "EB", "NB", "SB", "WB"], "shortest_values": ["EB", "NB", "SB", "WB", "EB&WB"], "average_length": 2.0047885075818037}]}, {"column_name": "Date", "number_non_empty_cells": 8771, "number_empty_cells": 0, "number_distinct_values": 137, "frequent_values": ["09/12/2017", "09/06/2017", "10/14/2015", "10/05/2016", "11/05/2015"], "dataTypes": [{"type": "Date/Time", "count": 8771, "max_value": "2018-03-29 00:00:00", "min_value": "2014-09-16 00:00:00"}]}, {"column_name": "Veh Class Type", "number_non_empty_cells": 8771, "number_empty_cells": 0, "number_distinct_values": 7, "frequent_values": ["Auto", "Taxis", "Commercial", "Medium Truck", "Heavy Truck"], "dataTypes": [{"type": "Text", "count": 8771, "longest_values": ["Medium Truck", "Heavy Truck", "Commercial", "School Bus", "Other Bus"], "shortest_values": ["Auto", "Taxis", "Other Bus", "Commercial", "School Bus"], "average_length": 8.714285714285714}]}, {"column_name": "12:00-1:00 AM", "number_non_empty_cells": 5495, "number_empty_cells": 3276, "number_distinct_values": 401, "frequent_values": ["None", "0", "1", "2", "3"], "dataTypes": [{"type": "Integer", "count": 5495, "max_val": 3567, "min_val": 0, "mean": 39.61383075523203, "std_dev": 153.10779953919632}, {"type": "Text", "count": 3276, "longest_values": ["None"], "shortest_values": ["None"], "average_length": 4.0}]}, {"column_name": "1:00-2:00AM", "number_non_empty_cells": 5495, "number_empty_cells": 3276, "number_distinct_values": 318, "frequent_values": ["None", "0", "1", "2", "3"], "dataTypes": [{"type": "Integer", "count": 5495, "max_val": 1637, "min_val": 0, "mean": 24.5557779799818, "std_dev": 87.45004778749913}, {"type": "Text", "count": 3276, "longest_values": ["None"], "shortest_values": ["None"], "average_length": 4.0}]}, {"column_name": "2:00-3:00AM", "number_non_empty_cells": 5495, "number_empty_cells": 3276, "number_distinct_values": 262, "frequent_values": ["None", "0", "1", "2", "3"], "dataTypes": [{"type": "Integer", "count": 5495, "max_val": 1031, "min_val": 0, "mean": 17.44695177434031, "std_dev": 59.92215294245112}, {"type": "Text", "count": 3276, "longest_values": ["None"], "shortest_values": ["None"], "average_length": 4.0}]}, {"column_name": "3:00-4:00AM", "number_non_empty_cells": 5495, "number_empty_cells": 3276, "number_distinct_values": 259, "frequent_values": ["None", "0", "1", "2", "3"], "dataTypes": [{"type": "Integer", "count": 5495, "max_val": 902, "min_val": 0, "mean": 16.287170154686077, "std_dev": 56.0404724735554}, {"type": "Text", "count": 3276, "longest_values": ["None"], "shortest_values": ["None"], "average_length": 4.0}]}, {"column_name": "4:00-5:00AM", "number_non_empty_cells": 5495, "number_empty_cells": 3276, "number_distinct_values": 303, "frequent_values": ["None", "0", "1", "2", "3"], "dataTypes": [{"type": "Integer", "count": 5495, "max_val": 1965, "min_val": 0, "mean": 24.818562329390353, "std_dev": 99.55049510227374}, {"type": "Text", "count": 3276, "longest_values": ["None"], "shortest_values": ["None"], "average_length": 4.0}]}, {"column_name": "5:00-6:00AM", "number_non_empty_cells": 5495, "number_empty_cells": 3276, "number_distinct_values": 418, "frequent_values": ["None", "0", "1", "2", "3"], "dataTypes": [{"type": "Integer", "count": 5495, "max_val": 5007, "min_val": 0, "mean": 52.90336669699727, "std_dev": 242.30708916972864}, {"type": "Text", "count": 3276, "longest_values": ["None"], "shortest_values": ["None"], "average_length": 4.0}]}, {"column_name": "6:00-7:00AM", "number_non_empty_cells": 5495, "number_empty_cells": 3276, "number_distinct_values": 557, "frequent_values": ["None", "0", "1", "2", "3"], "dataTypes": [{"type": "Integer", "count": 5495, "max_val": 6794, "min_val": 0, "mean": 100.86114649681528, "std_dev": 418.9465625260776}, {"type": "Text", "count": 3276, "longest_values": ["None"], "shortest_values": ["None"], "average_length": 4.0}]}, {"column_name": "7:00-8:00AM", "number_non_empty_cells": 5495, "number_empty_cells": 3276, "number_distinct_values": 684, "frequent_values": ["None", "0", "1", "3", "2"], "dataTypes": [{"type": "Integer", "count": 5495, "max_val": 6828, "min_val": 0, "mean": 133.03202911737944, "std_dev": 488.1633103915775}, {"type": "Text", "count": 3276, "longest_values": ["None"], "shortest_values": ["None"], "average_length": 4.0}]}, {"column_name": "8:00-9:00AM", "number_non_empty_cells": 5495, "number_empty_cells": 3276, "number_distinct_values": 683, "frequent_values": ["None", "0", "1", "2", "3"], "dataTypes": [{"type": "Integer", "count": 5495, "max_val": 6600, "min_val": 0, "mean": 131.40764331210192, "std_dev": 466.46368914881}, {"type": "Text", "count": 3276, "longest_values": ["None"], "shortest_values": ["None"], "average_length": 4.0}]}, {"column_name": "9:00-10:00AM", "number_non_empty_cells": 5446, "number_empty_cells": 3325, "number_distinct_values": 631, "frequent_values": ["None", "0", "1", "2", "3"], "dataTypes": [{"type": "Integer", "count": 5446, "max_val": 6164, "min_val": 0, "mean": 113.5749173705472, "std_dev": 401.463463095791}, {"type": "Text", "count": 3325, "longest_values": ["None"], "shortest_values": ["None"], "average_length": 4.0}]}, {"column_name": "10:00-11:00AM", "number_non_empty_cells": 5495, "number_empty_cells": 3276, "number_distinct_values": 606, "frequent_values": ["None", "0", "1", "3", "2"], "dataTypes": [{"type": "Integer", "count": 5495, "max_val": 5254, "min_val": 0, "mean": 103.95832575068243, "std_dev": 357.62091197668445}, {"type": "Text", "count": 3276, "longest_values": ["None"], "shortest_values": ["None"], "average_length": 4.0}]}, {"column_name": "11:00-12:00PM", "number_non_empty_cells": 5495, "number_empty_cells": 3276, "number_distinct_values": 608, "frequent_values": ["None", "0", "1", "2", "3"], "dataTypes": [{"type": "Integer", "count": 5495, "max_val": 5071, "min_val": 0, "mean": 101.98434940855323, "std_dev": 347.4713488996771}, {"type": "Text", "count": 3276, "longest_values": ["None"], "shortest_values": ["None"], "average_length": 4.0}]}, {"column_name": "12:00-1:00PM", "number_non_empty_cells": 5481, "number_empty_cells": 3290, "number_distinct_values": 615, "frequent_values": ["None", "0", "1", "2", "3"], "dataTypes": [{"type": "Integer", "count": 5481, "max_val": 4608, "min_val": 0, "mean": 103.88688195584747, "std_dev": 355.59766074323477}, {"type": "Text", "count": 3290, "longest_values": ["None"], "shortest_values": ["None"], "average_length": 4.0}]}, {"column_name": "1:00-2:00PM", "number_non_empty_cells": 5495, "number_empty_cells": 3276, "number_distinct_values": 624, "frequent_values": ["None", "0", "1", "2", "3"], "dataTypes": [{"type": "Integer", "count": 5495, "max_val": 5102, "min_val": 0, "mean": 108.17324840764331, "std_dev": 372.3502904769368}, {"type": "Text", "count": 3276, "longest_values": ["None"], "shortest_values": ["None"], "average_length": 4.0}]}, {"column_name": "2:00-3:00PM", "number_non_empty_cells": 5495, "number_empty_cells": 3276, "number_distinct_values": 647, "frequent_values": ["None", "0", "1", "2", "3"], "dataTypes": [{"type": "Integer", "count": 5495, "max_val": 6481, "min_val": 0, "mean": 121.05150136487715, "std_dev": 430.4178916088655}, {"type": "Text", "count": 3276, "longest_values": ["None"], "shortest_values": ["None"], "average_length": 4.0}]}, {"column_name": "3:00-4:00PM", "number_non_empty_cells": 5495, "number_empty_cells": 3276, "number_distinct_values": 690, "frequent_values": ["None", "0", "1", "2", "3"], "dataTypes": [{"type": "Integer", "count": 5495, "max_val": 6875, "min_val": 0, "mean": 130.47970882620564, "std_dev": 463.89778898516505}, {"type": "Text", "count": 3276, "longest_values": ["None"], "shortest_values": ["None"], "average_length": 4.0}]}, {"column_name": "4:00-5:00PM", "number_non_empty_cells": 5495, "number_empty_cells": 3276, "number_distinct_values": 708, "frequent_values": ["None", "0", "1", "2", "3"], "dataTypes": [{"type": "Integer", "count": 5495, "max_val": 6717, "min_val": 0, "mean": 134.55559599636032, "std_dev": 475.7615026670292}, {"type": "Text", "count": 3276, "longest_values": ["None"], "shortest_values": ["None"], "average_length": 4.0}]}, {"column_name": "5:00-6:00PM", "number_non_empty_cells": 5495, "number_empty_cells": 3276, "number_distinct_values": 706, "frequent_values": ["None", "0", "1", "2", "3"], "dataTypes": [{"type": "Integer", "count": 5495, "max_val": 8293, "min_val": 0, "mean": 134.8722474977252, "std_dev": 486.95450645561766}, {"type": "Text", "count": 3276, "longest_values": ["None"], "shortest_values": ["None"], "average_length": 4.0}]}, {"column_name": "6:00-7:00PM", "number_non_empty_cells": 5495, "number_empty_cells": 3276, "number_distinct_values": 694, "frequent_values": ["None", "0", "1", "2", "3"], "dataTypes": [{"type": "Integer", "count": 5495, "max_val": 7798, "min_val": 0, "mean": 128.81601455868972, "std_dev": 474.26436032153015}, {"type": "Text", "count": 3276, "longest_values": ["None"], "shortest_values": ["None"], "average_length": 4.0}]}, {"column_name": "7:00-8:00PM", "number_non_empty_cells": 5495, "number_empty_cells": 3276, "number_distinct_values": 656, "frequent_values": ["None", "0", "1", "2", "3"], "dataTypes": [{"type": "Integer", "count": 5495, "max_val": 6720, "min_val": 0, "mean": 114.8687898089172, "std_dev": 436.08784103206216}, {"type": "Text", "count": 3276, "longest_values": ["None"], "shortest_values": ["None"], "average_length": 4.0}]}, {"column_name": "8:00-9:00PM", "number_non_empty_cells": 5467, "number_empty_cells": 3304, "number_distinct_values": 604, "frequent_values": ["None", "0", "1", "2", "3"], "dataTypes": [{"type": "Integer", "count": 5467, "max_val": 7249, "min_val": 0, "mean": 98.78489116517285, "std_dev": 388.7242428272034}, {"type": "Text", "count": 3304, "longest_values": ["None"], "shortest_values": ["None"], "average_length": 4.0}]}, {"column_name": "9:00-10:00PM", "number_non_empty_cells": 5495, "number_empty_cells": 3276, "number_distinct_values": 554, "frequent_values": ["None", "0", "1", "2", "3"], "dataTypes": [{"type": "Integer", "count": 5495, "max_val": 5362, "min_val": 0, "mean": 84.91519563239308, "std_dev": 334.925838299691}, {"type": "Text", "count": 3276, "longest_values": ["None"], "shortest_values": ["None"], "average_length": 4.0}]}, {"column_name": "10:00-11:00PM", "number_non_empty_cells": 5495, "number_empty_cells": 3276, "number_distinct_values": 517, "frequent_values": ["None", "0", "1", "2", "3"], "dataTypes": [{"type": "Integer", "count": 5495, "max_val": 4888, "min_val": 0, "mean": 72.82638762511374, "std_dev": 293.57544411247693}, {"type": "Text", "count": 3276, "longest_values": ["None"], "shortest_values": ["None"], "average_length": 4.0}]}, {"column_name": "11:00-12:00AM", "number_non_empty_cells": 5495, "number_empty_cells": 3276, "number_distinct_values": 474, "frequent_values": ["None", "0", "1", "2", "3"], "dataTypes": [{"type": "Integer", "count": 5495, "max_val": 4891, "min_val": 0, "mean": 58.12484076433121, "std_dev": 229.09348838719023}, {"type": "Text", "count": 3276, "longest_values": ["None"], "shortest_values": ["None"], "average_length": 4.0}]}], "col_count": 33, "key_column_candidates": ["4:00-5:00PM"], "end time": "2019-12-04 23:24:40.939459"}