{"start time": "2019-12-04 23:35:31.876877", "row_count": 210, "dataset_name": "a2nf-cvfm.tsv.gz", "columns": [{"column_name": "Borough", "number_non_empty_cells": 210, "number_empty_cells": 0, "number_distinct_values": 5, "frequent_values": ["BRONX", "BROOKLYN", "MANHATTAN", "QUEENS", "STATEN ISLAND"], "dataTypes": [{"type": "Text", "count": 210, "longest_values": ["STATEN ISLAND", "MANHATTAN", "BROOKLYN", "QUEENS", "BRONX"], "shortest_values": ["BRONX", "QUEENS", "BROOKLYN", "MANHATTAN", "STATEN ISLAND"], "average_length": 8.2}]}, {"column_name": "Grade", "number_non_empty_cells": 210, "number_empty_cells": 0, "number_distinct_values": 7, "frequent_values": ["3", "4", "5", "6", "7"], "dataTypes": [{"type": "Integer", "count": 180, "max_val": 8, "min_val": 3, "mean": 5.5, "std_dev": 1.7125889448010425}, {"type": "Text", "count": 30, "longest_values": ["All Grades"], "shortest_values": ["All Grades"], "average_length": 10.0}]}, {"column_name": "Year", "number_non_empty_cells": 210, "number_empty_cells": 0, "number_distinct_values": 6, "frequent_values": ["2006", "2007", "2008", "2009", "2010"], "dataTypes": [{"type": "Integer", "count": 210, "max_val": 2011, "min_val": 2006, "mean": 2008.5, "std_dev": 1.7119059581558147}]}, {"column_name": "Category", "number_non_empty_cells": 210, "number_empty_cells": 0, "number_distinct_values": 1, "frequent_values": ["All Students"], "dataTypes": [{"type": "Text", "count": 210, "longest_values": ["All Students"], "shortest_values": ["All Students"], "average_length": 12.0}]}, {"column_name": "Number Tested", "number_non_empty_cells": 210, "number_empty_cells": 0, "number_distinct_values": 206, "frequent_values": ["4305", "4260", "4300", "25881", "16445"], "dataTypes": [{"type": "Integer", "count": 210, "max_val": 139780, "min_val": 4133, "mean": 24529.32380952381, "std_dev": 29949.87744652906}]}, {"column_name": "Mean Scale Score", "number_non_empty_cells": 210, "number_empty_cells": 0, "number_distinct_values": 54, "frequent_values": ["684", "674", "681", "679", "675"], "dataTypes": [{"type": "Integer", "count": 210, "max_val": 696, "min_val": 627, "mean": 672.7714285714286, "std_dev": 14.321501313175744}]}, {"column_name": "Level 1 #", "number_non_empty_cells": 210, "number_empty_cells": 0, "number_distinct_values": 205, "frequent_values": ["1031", "1837", "512", "593", "327"], "dataTypes": [{"type": "Integer", "count": 210, "max_val": 21859, "min_val": 54, "mean": 2286.133333333333, "std_dev": 3360.397844886386}]}, {"column_name": "Level 1 %", "number_non_empty_cells": 210, "number_empty_cells": 0, "number_distinct_values": 123, "frequent_values": ["6.4", "10.4", "7.7", "7.8", "5.4"], "dataTypes": [{"type": "Integer", "count": 15, "max_val": 24, "min_val": 2, "mean": 8.733333333333333, "std_dev": 6.452758730813917}, {"type": "Real", "count": 195, "max_val": 33.1, "min_val": 0.9, "mean": 8.993846153846153, "std_dev": 5.3812928233312265}]}, {"column_name": "Level 2 #", "number_non_empty_cells": 210, "number_empty_cells": 0, "number_distinct_values": 209, "frequent_values": ["1566", "3257", "2640", "2061", "6337"], "dataTypes": [{"type": "Integer", "count": 210, "max_val": 47267, "min_val": 258, "mean": 6312.552380952381, "std_dev": 8379.203922951785}]}, {"column_name": "Level 2 %", "number_non_empty_cells": 210, "number_empty_cells": 0, "number_distinct_values": 158, "frequent_values": ["30", "34.6", "25.2", "31.2", "14.3"], "dataTypes": [{"type": "Integer", "count": 21, "max_val": 41, "min_val": 9, "mean": 29.095238095238095, "std_dev": 8.389903228910104}, {"type": "Real", "count": 189, "max_val": 48.8, "min_val": 5.3, "mean": 24.806878306878307, "std_dev": 10.252052482152738}]}, {"column_name": "Level 3 #", "number_non_empty_cells": 210, "number_empty_cells": 0, "number_distinct_values": 209, "frequent_values": ["4410", "8618", "8996", "10447", "11295"], "dataTypes": [{"type": "Integer", "count": 210, "max_val": 73773, "min_val": 1376, "mean": 10843.914285714285, "std_dev": 13656.501693675591}]}, {"column_name": "Level 3 %", "number_non_empty_cells": 210, "number_empty_cells": 0, "number_distinct_values": 166, "frequent_values": ["36.4", "52.4", "49", "36.6", "54.7"], "dataTypes": [{"type": "Integer", "count": 22, "max_val": 59, "min_val": 29, "mean": 46.22727272727273, "std_dev": 8.176224639199278}, {"type": "Real", "count": 188, "max_val": 71.4, "min_val": 23.1, "mean": 44.293617021276596, "std_dev": 10.138899607103193}]}, {"column_name": "Level 4 #", "number_non_empty_cells": 210, "number_empty_cells": 0, "number_distinct_values": 208, "frequent_values": ["374", "1127", "2508", "3308", "2458"], "dataTypes": [{"type": "Integer", "count": 210, "max_val": 39142, "min_val": 364, "mean": 5086.72380952381, "std_dev": 6817.622855294802}]}, {"column_name": "Level 4 %", "number_non_empty_cells": 210, "number_empty_cells": 0, "number_distinct_values": 152, "frequent_values": ["29.6", "21.5", "26.5", "12.4", "10.4"], "dataTypes": [{"type": "Integer", "count": 24, "max_val": 41, "min_val": 3, "mean": 21.208333333333332, "std_dev": 8.787239595580909}, {"type": "Real", "count": 186, "max_val": 42.3, "min_val": 2.2, "mean": 21.301612903225806, "std_dev": 8.590909562683743}]}, {"column_name": "Level 3+4 #", "number_non_empty_cells": 210, "number_empty_cells": 0, "number_distinct_values": 207, "frequent_values": ["6676", "17344", "3255", "11126", "12304"], "dataTypes": [{"type": "Integer", "count": 210, "max_val": 106961, "min_val": 2169, "mean": 15930.638095238095, "std_dev": 20077.283377264514}]}, {"column_name": "Level 3+4 %", "number_non_empty_cells": 210, "number_empty_cells": 0, "number_distinct_values": 166, "frequent_values": ["69.2", "82.5", "61.8", "81.4", "43.4"], "dataTypes": [{"type": "Integer", "count": 23, "max_val": 91, "min_val": 31, "mean": 68.04347826086956, "std_dev": 13.788922632018016}, {"type": "Real", "count": 187, "max_val": 93.8, "min_val": 25.4, "mean": 65.50534759358288, "std_dev": 14.835400602425372}]}], "col_count": 17, "key_column_candidates": ["Level 2 #", "Level 3 #"], "end time": "2019-12-04 23:35:33.917746"}