{"start time": "2019-12-05 01:25:04.514280", "row_count": 1522, "dataset_name": "axb2-9jkb.tsv.gz", "columns": [{"column_name": "DBN", "number_non_empty_cells": 1522, "number_empty_cells": 0, "number_distinct_values": 1522, "frequent_values": ["01M015", "01M019", "01M020", "01M034", "01M063"], "dataTypes": [{"type": "Text", "count": 1489, "longest_values": ["01M063", "01M064", "01M110", "01M134", "01M140"], "shortest_values": ["01M063", "01M064", "01M110", "01M134", "01M140"], "average_length": 6.0}, {"type": "Date/Time", "count": 33, "max_value": "2019-12-05 00:06:52", "min_value": "2019-12-05 00:01:15"}]}, {"column_name": "School Name", "number_non_empty_cells": 1522, "number_empty_cells": 0, "number_distinct_values": 1518, "frequent_values": ["PS 360", "PS 212", "PS 253", "PS 376", "PS 015 ROBERTO CLEMENTE"], "dataTypes": [{"type": "Text", "count": 1522, "longest_values": ["ENGLISH LANGUAGE LEARNERS AND INTERNATIONAL SUPPORT PREPARATORY ACADEMY (ELLIS)", "SCIENCE SKILLS CENTER HIGH SCHOOL FOR SCIENCE, TECHNOLOGY AND THE CREATIVE ARTS", "ACADEMY FOR COLLEGE PREPARATION AND CAREER EXPLORATION: A COLLEGE BOARD SCHOOL", "CITY POLYTECHNIC HIGH SCHOOL OF ENGINEERING, ARCHITECTURE, AND TECHNOLOGY", "KNOWLEDGE AND POWER PREPARATORY ACADEMY INTERNATIONAL HIGH SCHOOL (KAPPA)"], "shortest_values": ["KAPPA", "PS 62", "PS 66", "PS 78", "PS 89"], "average_length": 27.304204993429696}]}, {"column_name": "School Pupil-Teacher Ratio", "number_non_empty_cells": 1522, "number_empty_cells": 0, "number_distinct_values": 151, "frequent_values": ["14.5", "13.5", "12.9", "13.4", "12.3"], "dataTypes": [{"type": "Integer", "count": 156, "max_val": 20, "min_val": 6, "mean": 13.628205128205128, "std_dev": 2.647501436151668}, {"type": "Real", "count": 1366, "max_val": 25.6, "min_val": 3.9, "mean": 13.52467057101025, "std_dev": 2.6305445336301925}]}], "col_count": 4, "key_column_candidates": ["DBN"], "end time": "2019-12-05 01:25:05.065606"}