{"start time": "2019-12-05 03:43:30.659595", "row_count": 34, "dataset_name": "exe6-f2vx.tsv.gz", "columns": [{"column_name": "Community School District", "number_non_empty_cells": 34, "number_empty_cells": 0, "number_distinct_values": 34, "frequent_values": ["01", "02", "03", "04", "05"], "dataTypes": [{"type": "Integer", "count": 33, "max_val": 75, "min_val": 1, "mean": 18.272727272727273, "std_dev": 13.74607381962375}, {"type": "Text", "count": 1, "longest_values": ["Citywide"], "shortest_values": ["Citywide"], "average_length": 8.0}]}, {"column_name": "# of Graduates", "number_non_empty_cells": 34, "number_empty_cells": 0, "number_distinct_values": 34, "frequent_values": ["813", "7483", "2050", "724", "754"], "dataTypes": [{"type": "Integer", "count": 34, "max_val": 59869, "min_val": 147, "mean": 3521.705882352941, "std_dev": 10047.854716093476}]}, {"column_name": "# of Graduates that Completed 2+ Credits in Arts", "number_non_empty_cells": 34, "number_empty_cells": 0, "number_distinct_values": 34, "frequent_values": ["813", "7467", "2050", "724", "753"], "dataTypes": [{"type": "Integer", "count": 34, "max_val": 59803, "min_val": 146, "mean": 3517.823529411765, "std_dev": 10036.652627640076}]}, {"column_name": "% of Graduates that Completed 2+ Credits in Arts", "number_non_empty_cells": 34, "number_empty_cells": 0, "number_distinct_values": 5, "frequent_values": ["1", "0.999", "0.998", "0.996", "0.994"], "dataTypes": [{"type": "Integer", "count": 13, "max_val": 1, "min_val": 1, "mean": 1, "std_dev": 0.0}, {"type": "Real", "count": 21, "max_val": 0.999, "min_val": 0.994, "mean": 0.9981904761904762, "std_dev": 0.0013273676061682253}]}, {"column_name": "# of 8th Grade Students", "number_non_empty_cells": 34, "number_empty_cells": 0, "number_distinct_values": 34, "frequent_values": ["826", "2,233", "1,293", "1,000", "877"], "dataTypes": [{"type": "Integer", "count": 5, "max_val": 986, "min_val": 478, "mean": 807.4, "std_dev": 193.33339080458916}, {"type": "Text", "count": 3, "longest_values": ["65,504", "1,000", "na"], "shortest_values": ["na", "1,000", "65,504"], "average_length": 4.333333333333333}, {"type": "Date/Time", "count": 26, "max_value": "2048-02-05 00:00:00", "min_value": "0123-03-05 00:00:00"}]}, {"column_name": "# of 8th Grade Students that Received 2 Half-units of Instruction in Arts", "number_non_empty_cells": 34, "number_empty_cells": 0, "number_distinct_values": 34, "frequent_values": ["656", "2,110", "1,124", "901", "733"], "dataTypes": [{"type": "Integer", "count": 9, "max_val": 983, "min_val": 353, "mean": 778.8888888888889, "std_dev": 193.81656562613813}, {"type": "Text", "count": 2, "longest_values": ["56,917", "na"], "shortest_values": ["na", "56,917"], "average_length": 4.0}, {"type": "Date/Time", "count": 23, "max_value": "2019-04-20 00:00:00", "min_value": "0110-02-05 00:00:00"}]}, {"column_name": "% of 8th Grade Students that Received 2 Half-units of Instruction in Arts", "number_non_empty_cells": 34, "number_empty_cells": 0, "number_distinct_values": 33, "frequent_values": ["86.9%", "79.4%", "94.5%", "90.1%", "83.6%"], "dataTypes": [{"type": "Text", "count": 34, "longest_values": ["66.5%", "67.9%", "71.5%", "72.9%", "73.8%"], "shortest_values": ["na", "66.5%", "67.9%", "71.5%", "72.9%"], "average_length": 4.911764705882353}]}, {"column_name": "# of 8th Grade Students that Received 2 Half-units of Instruction in Arts in Two Different Disciplines", "number_non_empty_cells": 34, "number_empty_cells": 0, "number_distinct_values": 34, "frequent_values": ["374", "1,152", "305", "318", "302"], "dataTypes": [{"type": "Integer", "count": 21, "max_val": 947, "min_val": 125, "mean": 545.4761904761905, "std_dev": 212.78336848720556}, {"type": "Text", "count": 2, "longest_values": ["29,672", "na"], "shortest_values": ["na", "29,672"], "average_length": 4.0}, {"type": "Date/Time", "count": 11, "max_value": "2052-01-05 00:00:00", "min_value": "0123-02-05 00:00:00"}]}, {"column_name": "% of 8th Grade Students that Received 2 Half-units of Instruction in Arts in Two Different Disciplines", "number_non_empty_cells": 34, "number_empty_cells": 0, "number_distinct_values": 31, "frequent_values": ["45.3%", "20.6%", "48.2%", "51.6%", "23.6%"], "dataTypes": [{"type": "Text", "count": 34, "longest_values": ["18.2%", "20.6%", "23.6%", "26.2%", "31.8%"], "shortest_values": ["na", "18.2%", "20.6%", "23.6%", "26.2%"], "average_length": 4.911764705882353}]}, {"column_name": "# of Schools Serving Grades 1-5", "number_non_empty_cells": 34, "number_empty_cells": 0, "number_distinct_values": 24, "frequent_values": ["22", "21", "18", "26", "29"], "dataTypes": [{"type": "Integer", "count": 33, "max_val": 798, "min_val": 13, "mean": 48.36363636363637, "std_dev": 134.80699587322476}, {"type": "Text", "count": 1, "longest_values": ["na"], "shortest_values": ["na"], "average_length": 2.0}]}, {"column_name": "# of Schools Serving Grades 1-5 that Provided Arts Instruction in All Four Disciplines (Music, Dance, Theater, Visual Arts)", "number_non_empty_cells": 34, "number_empty_cells": 0, "number_distinct_values": 18, "frequent_values": ["10", "8", "4", "7", "6"], "dataTypes": [{"type": "Integer", "count": 33, "max_val": 345, "min_val": 4, "mean": 20.90909090909091, "std_dev": 58.41626680362865}, {"type": "Text", "count": 1, "longest_values": ["na"], "shortest_values": ["na"], "average_length": 2.0}]}, {"column_name": "% of Schools Serving Grades 1-5 that Provided Arts Instruction in All Four Disciplines (Music, Dance, Theater, Visual Arts)", "number_non_empty_cells": 34, "number_empty_cells": 0, "number_distinct_values": 31, "frequent_values": ["55.6%", "40.0%", "42.9%", "66.7%", "45.5%"], "dataTypes": [{"type": "Text", "count": 34, "longest_values": ["23.5%", "24.1%", "24.2%", "25.0%", "26.1%"], "shortest_values": ["na", "23.5%", "24.1%", "24.2%", "25.0%"], "average_length": 4.911764705882353}]}, {"column_name": "# of Schools Serving Grade 6", "number_non_empty_cells": 34, "number_empty_cells": 0, "number_distinct_values": 19, "frequent_values": ["12", "18", "15", "22", "19"], "dataTypes": [{"type": "Integer", "count": 33, "max_val": 509, "min_val": 7, "mean": 30.848484848484848, "std_dev": 85.98223697809668}, {"type": "Text", "count": 1, "longest_values": ["na"], "shortest_values": ["na"], "average_length": 2.0}]}, {"column_name": "# of Schools Serving Grade 6 that Provided Arts Instruction in All Four Disciplines (Dance, Music, Theater, Visual Arts)", "number_non_empty_cells": 34, "number_empty_cells": 0, "number_distinct_values": 7, "frequent_values": ["1", "0", "3", "2", "6"], "dataTypes": [{"type": "Integer", "count": 33, "max_val": 40, "min_val": 0, "mean": 2.4242424242424243, "std_dev": 6.874001304872872}, {"type": "Text", "count": 1, "longest_values": ["na"], "shortest_values": ["na"], "average_length": 2.0}]}, {"column_name": "% of Schools Serving Grade 6 that Provided Arts Instruction in All Four Disciplines (Dance, Music, Theater, Visual Arts)", "number_non_empty_cells": 34, "number_empty_cells": 0, "number_distinct_values": 7, "frequent_values": ["8.3%", "0.0%", "25.0%", "16.7%", "50.0%"], "dataTypes": [{"type": "Text", "count": 34, "longest_values": ["16.7%", "25.0%", "50.0%", "0.0%", "7.9%"], "shortest_values": ["na", "0.0%", "7.9%", "8.3%", "16.7%"], "average_length": 4.205882352941177}]}, {"column_name": "Number of Full-Time Teachers Certified in Dance", "number_non_empty_cells": 34, "number_empty_cells": 0, "number_distinct_values": 12, "frequent_values": ["3", "1", "2", "4", "6"], "dataTypes": [{"type": "Integer", "count": 33, "max_val": 138, "min_val": 1, "mean": 8.363636363636363, "std_dev": 23.42383692659331}, {"type": "Text", "count": 1, "longest_values": ["na"], "shortest_values": ["na"], "average_length": 2.0}]}, {"column_name": "Number of Full-Time Teachers Certified in Music", "number_non_empty_cells": 34, "number_empty_cells": 0, "number_distinct_values": 24, "frequent_values": ["9", "11", "15", "34", "21"], "dataTypes": [{"type": "Integer", "count": 33, "max_val": 606, "min_val": 2, "mean": 36.72727272727273, "std_dev": 102.82791228773705}, {"type": "Text", "count": 1, "longest_values": ["na"], "shortest_values": ["na"], "average_length": 2.0}]}, {"column_name": "Number of Full-Time Teachers Certified in Theater", "number_non_empty_cells": 34, "number_empty_cells": 0, "number_distinct_values": 14, "frequent_values": ["2", "1", "3", "5", "8"], "dataTypes": [{"type": "Integer", "count": 33, "max_val": 131, "min_val": 0, "mean": 7.9393939393939394, "std_dev": 22.322829393273874}, {"type": "Text", "count": 1, "longest_values": ["na"], "shortest_values": ["na"], "average_length": 2.0}]}, {"column_name": "Number of Full-Time Teachers Certified in Visual Arts", "number_non_empty_cells": 34, "number_empty_cells": 0, "number_distinct_values": 27, "frequent_values": ["11", "20", "27", "22", "10"], "dataTypes": [{"type": "Integer", "count": 33, "max_val": 839, "min_val": 5, "mean": 50.84848484848485, "std_dev": 142.47458571884874}, {"type": "Text", "count": 1, "longest_values": ["na"], "shortest_values": ["na"], "average_length": 2.0}]}, {"column_name": "Number of Part-Time Teachers Certified in Dance", "number_non_empty_cells": 34, "number_empty_cells": 0, "number_distinct_values": 9, "frequent_values": ["2", "3", "4", "5", "0"], "dataTypes": [{"type": "Integer", "count": 33, "max_val": 95, "min_val": 0, "mean": 5.757575757575758, "std_dev": 16.13813477262456}, {"type": "Text", "count": 1, "longest_values": ["na"], "shortest_values": ["na"], "average_length": 2.0}]}, {"column_name": "Number of Part-Time Teachers Certified in Music", "number_non_empty_cells": 34, "number_empty_cells": 0, "number_distinct_values": 15, "frequent_values": ["5", "2", "6", "8", "3"], "dataTypes": [{"type": "Integer", "count": 33, "max_val": 218, "min_val": 2, "mean": 13.212121212121213, "std_dev": 36.94570135326772}, {"type": "Text", "count": 1, "longest_values": ["na"], "shortest_values": ["na"], "average_length": 2.0}]}, {"column_name": "Number of Part-Time Teachers Certified in Theater", "number_non_empty_cells": 34, "number_empty_cells": 0, "number_distinct_values": 9, "frequent_values": ["4", "2", "1", "3", "0"], "dataTypes": [{"type": "Integer", "count": 33, "max_val": 98, "min_val": 0, "mean": 5.9393939393939394, "std_dev": 16.79274284091828}, {"type": "Text", "count": 1, "longest_values": ["na"], "shortest_values": ["na"], "average_length": 2.0}]}, {"column_name": "Number of Part-Time Teachers Certified in Visual Arts", "number_non_empty_cells": 34, "number_empty_cells": 0, "number_distinct_values": 17, "frequent_values": ["10", "7", "4", "2", "12"], "dataTypes": [{"type": "Integer", "count": 33, "max_val": 305, "min_val": 2, "mean": 18.484848484848484, "std_dev": 51.983844372627686}, {"type": "Text", "count": 1, "longest_values": ["na"], "shortest_values": ["na"], "average_length": 2.0}]}], "col_count": 24, "key_column_candidates": ["Community School District", "# of Graduates", "# of Graduates that Completed 2+ Credits in Arts", "# of 8th Grade Students", "# of 8th Grade Students that Received 2 Half-units of Instruction in Arts", "# of 8th Grade Students that Received 2 Half-units of Instruction in Arts in Two Different Disciplines"], "end time": "2019-12-05 03:43:32.545858"}