{"start time": "2019-12-05 03:47:03.625879", "row_count": 18794, "dataset_name": "ezaf-3uhs.tsv.gz", "columns": [{"column_name": "DBN", "number_non_empty_cells": 18794, "number_empty_cells": 0, "number_distinct_values": 903, "frequent_values": ["12X242", "08X367", "12X271", "10X141", "07X551"], "dataTypes": [{"type": "Text", "count": 18672, "longest_values": ["01M140", "01M184", "01M188", "01M292", "01M301"], "shortest_values": ["01M140", "01M184", "01M188", "01M292", "01M301"], "average_length": 6.0}, {"type": "Date/Time", "count": 122, "max_value": "2019-12-05 00:06:52", "min_value": "2019-12-05 00:01:34"}]}, {"column_name": "School Name", "number_non_empty_cells": 18794, "number_empty_cells": 0, "number_distinct_values": 903, "frequent_values": ["MOTT HALL V", "ARCHIMEDES ACADEMY FOR MATH, SCIENCE AND TECHNOLOGY APPLICATIONS", "EAST BRONX ACADEMY FOR THE FUTURE", "RIVERDALE / KINGSBRIDGE ACADEMY (MIDDLE SCHOOL / HIGH SCHOOL 141)", "THE URBAN ASSEMBLY BRONX ACADEMY OF LETTERS"], "dataTypes": [{"type": "Text", "count": 18794, "longest_values": ["ENGLISH LANGUAGE LEARNERS AND INTERNATIONAL SUPPORT PREPARATORY ACADEMY (ELLIS)", "SCIENCE SKILLS CENTER HIGH SCHOOL FOR SCIENCE, TECHNOLOGY AND THE CREATIVE ARTS", "ACADEMY FOR COLLEGE PREPARATION AND CAREER EXPLORATION: A COLLEGE BOARD SCHOOL", "CITY POLYTECHNIC HIGH SCHOOL OF ENGINEERING, ARCHITECTURE, AND TECHNOLOGY", "KNOWLEDGE AND POWER PREPARATORY ACADEMY INTERNATIONAL HIGH SCHOOL (KAPPA)"], "shortest_values": ["KAPPA", "KAPPA V", "P.S. 66", "I.S. 077", "I.S. 230"], "average_length": 34.160849207193785}]}, {"column_name": "Grade Level", "number_non_empty_cells": 18794, "number_empty_cells": 0, "number_distinct_values": 2, "frequent_values": ["HS Core", "MS Core"], "dataTypes": [{"type": "Text", "count": 18794, "longest_values": ["HS Core", "MS Core"], "shortest_values": ["HS Core", "MS Core"], "average_length": 7.0}]}, {"column_name": "Program Type", "number_non_empty_cells": 18794, "number_empty_cells": 0, "number_distinct_values": 5, "frequent_values": ["Gen Ed", "ICT", "SC", "Accelerated", "ICT & Acc"], "dataTypes": [{"type": "Text", "count": 18794, "longest_values": ["Accelerated", "ICT & Acc", "Gen Ed", "ICT", "SC"], "shortest_values": ["SC", "ICT", "Gen Ed", "ICT & Acc", "Accelerated"], "average_length": 4.620357560923699}]}, {"column_name": "Department", "number_non_empty_cells": 18794, "number_empty_cells": 0, "number_distinct_values": 4, "frequent_values": ["English", "Science", "Math", "Social Studies"], "dataTypes": [{"type": "Text", "count": 18794, "longest_values": ["Social Studies", "English", "Science", "Math"], "shortest_values": ["Math", "English", "Science", "Social Studies"], "average_length": 7.867244865382569}]}, {"column_name": "Subject", "number_non_empty_cells": 18794, "number_empty_cells": 0, "number_distinct_values": 29, "frequent_values": ["MS Math Core", "MS English Core", "MS Science Core", "MS Social Studies Core", "HS Global History"], "dataTypes": [{"type": "Text", "count": 18794, "longest_values": ["HS Social Studies Other", "MS Social Studies Other", "MS Social Studies Core", "HS Living Environment", "HS Other Life Science"], "shortest_values": ["HS Physics", "HS Geometry", "HS Algebra I", "HS Chemistry", "HS Economics"], "average_length": 15.06161540917314}]}, {"column_name": "Number of Students", "number_non_empty_cells": 18794, "number_empty_cells": 0, "number_distinct_values": 849, "frequent_values": ["32", "24", "30", "31", "34"], "dataTypes": [{"type": "Integer", "count": 18794, "max_val": 4469, "min_val": 5, "mean": 109.50915185697563, "std_dev": 165.89107068444142}]}, {"column_name": "Number of Classes", "number_non_empty_cells": 18794, "number_empty_cells": 0, "number_distinct_values": 60, "frequent_values": ["1", "2", "3", "4", "5"], "dataTypes": [{"type": "Integer", "count": 18794, "max_val": 137, "min_val": 1, "mean": 4.312493348941151, "std_dev": 5.554343142771643}]}, {"column_name": "Average Class Size", "number_non_empty_cells": 18794, "number_empty_cells": 0, "number_distinct_values": 1379, "frequent_values": ["26", "28", "27", "30", "29"], "dataTypes": [{"type": "Integer", "count": 9036, "max_val": 96, "min_val": 5, "mean": 22.663899955732624, "std_dev": 8.106323507930412}, {"type": "Real", "count": 9758, "max_val": 55.25, "min_val": 5.333333, "mean": 24.387211906538226, "std_dev": 6.589775982843748}]}], "col_count": 10, "key_column_candidates": ["Average Class Size"], "end time": "2019-12-05 03:47:11.474070"}