{"start time": "2019-12-06 15:45:07.910911", "row_count": 228, "dataset_name": "xkuq-9uzf.tsv.gz", "columns": [{"column_name": "Grade Level", "number_non_empty_cells": 228, "number_empty_cells": 0, "number_distinct_values": 10, "frequent_values": ["K-8 SC", "1", "4", "5", "6"], "dataTypes": [{"type": "Integer", "count": 174, "max_val": 8, "min_val": 1, "mean": 4.522988505747127, "std_dev": 2.3002991084436006}, {"type": "Text", "count": 54, "longest_values": ["K-8 SC", "K"], "shortest_values": ["K", "K-8 SC"], "average_length": 4.2407407407407405}]}, {"column_name": "Program Type", "number_non_empty_cells": 228, "number_empty_cells": 0, "number_distinct_values": 7, "frequent_values": ["Gen Ed/ICT/G&T", "SC 12:1:1", "SC 12:1", "SC 15:1", "SC 8:1:1"], "dataTypes": [{"type": "Text", "count": 228, "longest_values": ["Gen Ed/ICT/G&T", "SC 12:1:1", "SC 12:1:4", "SC 6:1:1", "SC 8:1:1"], "shortest_values": ["SC 12:1", "SC 15:1", "SC 6:1:1", "SC 8:1:1", "SC 12:1:1"], "average_length": 13.070175438596491}]}, {"column_name": "Class Size", "number_non_empty_cells": 228, "number_empty_cells": 0, "number_distinct_values": 33, "frequent_values": ["15", "<15", "16", "17", "18"], "dataTypes": [{"type": "Integer", "count": 205, "max_val": 34, "min_val": 6, "mean": 22.360975609756096, "std_dev": 7.362893121725401}, {"type": "Text", "count": 23, "longest_values": ["< 6", "<15", ">15", ">34"], "shortest_values": ["< 6", "<15", ">15", ">34"], "average_length": 3.0}]}, {"column_name": "Number of Students", "number_non_empty_cells": 228, "number_empty_cells": 0, "number_distinct_values": 218, "frequent_values": ["702", "495", "5016", "592", "1178"], "dataTypes": [{"type": "Integer", "count": 228, "max_val": 14040, "min_val": 3, "mean": 2668.622807017544, "std_dev": 2645.5293430003353}]}, {"column_name": "Number of Classes", "number_non_empty_cells": 228, "number_empty_cells": 0, "number_distinct_values": 147, "frequent_values": ["1", "2", "152", "139", "121"], "dataTypes": [{"type": "Integer", "count": 228, "max_val": 602, "min_val": 1, "mean": 115.01315789473684, "std_dev": 104.90140032842663}]}, {"column_name": "% of Students within Grade", "number_non_empty_cells": 228, "number_empty_cells": 0, "number_distinct_values": 110, "frequent_values": ["0.8", "0.3", "1.7", "1.1", "0.9"], "dataTypes": [{"type": "Integer", "count": 19, "max_val": 100, "min_val": 0, "mean": 15, "std_dev": 23.42126289412156}, {"type": "Real", "count": 209, "max_val": 37.5, "min_val": 0.1, "mean": 5.813875598086124, "std_dev": 6.769377371936102}]}], "col_count": 7, "key_column_candidates": ["Number of Students"], "end time": "2019-12-06 15:45:09.271190"}