{"start time": "2019-12-06 17:31:46.930548", "row_count": 13, "dataset_name": "yj3u-pw36.tsv.gz", "columns": [{"column_name": "Location", "number_non_empty_cells": 13, "number_empty_cells": 0, "number_distinct_values": 13, "frequent_values": ["1 Fordham Plaza, 7th floor", "1230 Zerega Avenue", "1790 Ocean Avenue, 3rd floor", "415 89th street", "1665 St. Mark's Avenue"], "dataTypes": [{"type": "Text", "count": 13, "longest_values": ["715 Ocean Terrace, Building A", "1790 Ocean Avenue, 3rd floor", "1 Fordham Plaza, 7th floor", "28-11 Queens Plaza North", "90-27 Sutphin Boulevard"], "shortest_values": ["415 89th street", "1230 Zerega Avenue", "30-48 Linden Place", "333 Seventh Avenue", "29 Fort Greene Place"], "average_length": 21.76923076923077}]}, {"column_name": "Phone Number", "number_non_empty_cells": 13, "number_empty_cells": 0, "number_distinct_values": 13, "frequent_values": ["718-935-2178  ", "718-935-2278  ", "718-935-2313   ", "718-935-2331  ", "718-935-2340  "], "dataTypes": [{"type": "Text", "count": 13, "longest_values": ["718-935-2386     ", "718-935-2393     ", "718-935-2313   ", "718-935-2383   ", "718-935-2385   "], "shortest_values": ["718-935-2371 ", "718-935-4908 ", "718-935-2178  ", "718-935-2278  ", "718-935-2331  "], "average_length": 14.692307692307692}]}, {"column_name": "Districts Served", "number_non_empty_cells": 13, "number_empty_cells": 0, "number_distinct_values": 13, "frequent_values": ["7, 9, 10 ", "8, 11, 12 ", "17, 18, 22", "20, 21 ", "19, 23, 32 "], "dataTypes": [{"type": "Integer", "count": 1, "max_val": 31, "min_val": 31, "mean": 31, "std_dev": "Cannot compute variance with only one datapoint"}, {"type": "Text", "count": 8, "longest_values": ["13,14,15,16, General Education Only", "13,14,15,16, Special Education Only", "19, 23, 32 ", "17, 18, 22", "27, 28, 29"], "shortest_values": ["24, 30", "20, 21 ", "25, 26  ", "17, 18, 22", "27, 28, 29"], "average_length": 15.25}, {"type": "Date/Time", "count": 4, "max_value": "2012-08-11 00:00:00", "min_value": "2004-01-02 00:00:00"}]}, {"column_name": "Borough", "number_non_empty_cells": 13, "number_empty_cells": 0, "number_distinct_values": 5, "frequent_values": ["3", "4", "2", "1", "5"], "dataTypes": [{"type": "Integer", "count": 13, "max_val": 5, "min_val": 1, "mean": 2.923076923076923, "std_dev": 1.1875421719907087}]}, {"column_name": "Postcode", "number_non_empty_cells": 11, "number_empty_cells": 2, "number_distinct_values": 12, "frequent_values": ["None", "10462", "11209", "11233", "11217"], "dataTypes": [{"type": "Integer", "count": 11, "max_val": 11435, "min_val": 10001, "mean": 10867.363636363636, "std_dev": 551.3130277305758}, {"type": "Text", "count": 2, "longest_values": ["None"], "shortest_values": ["None"], "average_length": 4.0}]}, {"column_name": "Latitude", "number_non_empty_cells": 11, "number_empty_cells": 2, "number_distinct_values": 12, "frequent_values": ["None", "40.833586", "40.619931", "40.673138", "40.688834"], "dataTypes": [{"type": "Real", "count": 11, "max_val": 40.833586, "min_val": 40.608517, "mean": 40.71783318181818, "std_dev": 0.07220004915070061}, {"type": "Text", "count": 2, "longest_values": ["None"], "shortest_values": ["None"], "average_length": 4.0}]}, {"column_name": "Longitude", "number_non_empty_cells": 11, "number_empty_cells": 2, "number_distinct_values": 12, "frequent_values": ["None", "-73.845099", "-74.028086", "-73.912024", "-73.976905"], "dataTypes": [{"type": "Real", "count": 11, "max_val": -73.808148, "min_val": -74.102078, "mean": -73.94352109090909, "std_dev": 0.08902735604459418}, {"type": "Text", "count": 2, "longest_values": ["None"], "shortest_values": ["None"], "average_length": 4.0}]}, {"column_name": "Community Board", "number_non_empty_cells": 11, "number_empty_cells": 2, "number_distinct_values": 9, "frequent_values": ["2", "None", "9", "10", "16"], "dataTypes": [{"type": "Integer", "count": 11, "max_val": 16, "min_val": 1, "mean": 6.818181818181818, "std_dev": 4.874796033029112}, {"type": "Text", "count": 2, "longest_values": ["None"], "shortest_values": ["None"], "average_length": 4.0}]}, {"column_name": "Council District", "number_non_empty_cells": 11, "number_empty_cells": 2, "number_distinct_values": 12, "frequent_values": ["None", "13", "43", "41", "35"], "dataTypes": [{"type": "Integer", "count": 11, "max_val": 50, "min_val": 3, "mean": 27, "std_dev": 14.953260514014994}, {"type": "Text", "count": 2, "longest_values": ["None"], "shortest_values": ["None"], "average_length": 4.0}]}, {"column_name": "Census Tract", "number_non_empty_cells": 11, "number_empty_cells": 2, "number_distinct_values": 11, "frequent_values": ["None", "33", "96", "160", "36501"], "dataTypes": [{"type": "Integer", "count": 11, "max_val": 36501, "min_val": 33, "mean": 5376.545454545455, "std_dev": 12050.255718146702}, {"type": "Text", "count": 2, "longest_values": ["None"], "shortest_values": ["None"], "average_length": 4.0}]}, {"column_name": "BIN", "number_non_empty_cells": 11, "number_empty_cells": 2, "number_distinct_values": 12, "frequent_values": ["None", "2027195", "3154215", "3039123", "3058752"], "dataTypes": [{"type": "Integer", "count": 11, "max_val": 5113169, "min_val": 1015097, "mean": 3073454, "std_dev": 1290616.5589803192}, {"type": "Text", "count": 2, "longest_values": ["None"], "shortest_values": ["None"], "average_length": 4.0}]}, {"column_name": "BBL", "number_non_empty_cells": 11, "number_empty_cells": 2, "number_distinct_values": 12, "frequent_values": ["None", "2038420002", "3060650043", "3014540054", "3020980013"], "dataTypes": [{"type": "Integer", "count": 11, "max_val": 5006830001, "min_val": 1008040001, "mean": 3028650016.181818, "std_dev": 1270359120.8243575}, {"type": "Text", "count": 2, "longest_values": ["None"], "shortest_values": ["None"], "average_length": 4.0}]}, {"column_name": "NTA", "number_non_empty_cells": 11, "number_empty_cells": 2, "number_distinct_values": 12, "frequent_values": ["None", "Westchester-Unionport                                                      ", "Bay Ridge                                                                  ", "Ocean Hill                                                                 ", "Fort Greene                                                                "], "dataTypes": [{"type": "Text", "count": 13, "longest_values": ["Bay Ridge                                                                  ", "DUMBO-Vinegar Hill-Downtown Brooklyn-Boerum Hill                           ", "Flushing                                                                   ", "Fort Greene                                                                ", "Jamaica                                                                    "], "shortest_values": ["None", "Bay Ridge                                                                  ", "DUMBO-Vinegar Hill-Downtown Brooklyn-Boerum Hill                           ", "Flushing                                                                   ", "Fort Greene                                                                "], "average_length": 64.07692307692308}]}], "col_count": 14, "key_column_candidates": ["Location", "Phone Number", "Districts Served"], "end time": "2019-12-06 17:31:48.853507"}